groot_rocker/__init__.py
groot_rocker/cli.py
groot_rocker/console.py
groot_rocker/core.py
groot_rocker/extensions.py
groot_rocker/os_detector.py
groot_rocker/version.py
groot_rocker/templates/Dockerfile.em
groot_rocker/templates/bash_cmd_snippet.Dockerfile.em
groot_rocker-0.4.1.dist-info/LICENSE
groot_rocker-0.4.1.dist-info/METADATA
groot_rocker-0.4.1.dist-info/WHEEL
groot_rocker-0.4.1.dist-info/entry_points.txt
groot_rocker-0.4.1.dist-info/top_level.txt
groot_rocker-0.4.1.dist-info/RECORD
